the_agreement.py
the_agreement-0.1.2.1.dist-info/LICENSE
the_agreement-0.1.2.1.dist-info/METADATA
the_agreement-0.1.2.1.dist-info/WHEEL
the_agreement-0.1.2.1.dist-info/top_level.txt
the_agreement-0.1.2.1.dist-info/RECORD
