Metadata-Version: 2.1
Name: the_agreement
Version: 0.1.2.1
Summary: A package that demonstrates a decorator for simulating a small part of female consent in China
Home-page: https://github.com/Locked-chess-official/the_agreement
Author: Huang Hao Hua
Author-email: 13140752715@163.com
License: MIT License
Requires-Python: >=3.8
License-File: LICENSE
